{
  "gitSyncId": "68b00db619976b28d4c6e970_b5481674-d1d1-41e3-aecd-e82697ceb122",
  "id": "Profile_Page_utils.getExperienceInterval",
  "pluginId": "js-plugin",
  "pluginType": "JS",
  "unpublishedAction": {
    "actionConfiguration": {
      "encodeParamsToggle": true,
      "jsArguments": [
        {
          "name": "intervals"
        }
      ],
      "paginationType": "NONE",
      "timeoutInMillisecond": 10000
    },
    "collectionId": "Profile_Page_utils",
    "confirmBeforeExecute": false,
    "datasource": {
      "isAutoGenerated": false,
      "name": "UNUSED_DATASOURCE",
      "pluginId": "js-plugin"
    },
    "dynamicBindingPathList": [
      {
        "key": "body"
      }
    ],
    "fullyQualifiedName": "utils.getExperienceInterval",
    "name": "getExperienceInterval",
    "pageId": "Profile_Page",
    "runBehaviour": "MANUAL",
    "userSetOnLoad": false
  }
}